MANIFEST.in
README.rst
requirements-test.txt
requirements.txt
setup.py
django_debug_toolbar_vcs_info.egg-info/PKG-INFO
django_debug_toolbar_vcs_info.egg-info/SOURCES.txt
django_debug_toolbar_vcs_info.egg-info/dependency_links.txt
django_debug_toolbar_vcs_info.egg-info/requires.txt
django_debug_toolbar_vcs_info.egg-info/top_level.txt
django_debug_toolbar_vcs_info.egg-info/zip-safe
tests/__init__.py
tests/settings.py
tests/urls.py
vcs_info_panel/__init__.py
vcs_info_panel/clients/__init__.py
vcs_info_panel/clients/base.py
vcs_info_panel/clients/git.py
vcs_info_panel/locale/ja/LC_MESSAGES/django.po
vcs_info_panel/panels/__init__.py
vcs_info_panel/panels/base.py
vcs_info_panel/templates/git.html
vcs_info_panel/tests/__init__.py
vcs_info_panel/tests/compatibility.py
vcs_info_panel/tests/test_clients/__init__.py
vcs_info_panel/tests/test_clients/test_git.py
vcs_info_panel/tests/test_panels/__init__.py
vcs_info_panel/tests/test_panels/test_base.py
vcs_info_panel/tests/test_panels/test_git.py