Metadata-Version: 1.1
Name: django-debug-toolbar-vcs-info
Version: 1.1.0
Summary: A Django Debug Toolbar panel to show VCS info
Home-page: https://github.com/giginet/django-debug-toolbar-vcs-info
Author: giginet
Author-email: giginet.net@gmail.com
License: MIT
Download-URL: https://github.com/giginet/django-debug-toolbar-vcs-info/tarball/master
Keywords: django django-debug-toolbar git vcs info revision hash panel
Platform: UNKNOWN
Classifier: Development Status :: 5 - Production/Stable
Classifier: Environment :: Web Environment
Classifier: Framework :: Django
Classifier: Intended Audience :: Developers
Classifier: License :: OSI Approved :: MIT License
Classifier: Programming Language :: Python
Classifier: Programming Language :: Python :: 2
Classifier: Programming Language :: Python :: 2.7
Classifier: Programming Language :: Python :: 3
Classifier: Programming Language :: Python :: 3.2
Classifier: Programming Language :: Python :: 3.3
Classifier: Programming Language :: Python :: 3.4
Classifier: Programming Language :: Python :: 3.5
Classifier: Topic :: Internet :: WWW/HTTP
Classifier: Topic :: Software Development :: Libraries
Classifier: Topic :: Software Development :: Libraries :: Application Frameworks
Classifier: Topic :: Software Development :: Libraries :: Python Modules
